s1292013_learn/__init__.py
s1292013_learn/statistics/__init__.py
s1292013_learn/statistics/itemFrequencies.py
s1292013_learn/visualization/__init__.py
s1292013_learn/visualization/heatMap.py
s1292013_learn-2024.7.29.1.dist-info/LICENSE
s1292013_learn-2024.7.29.1.dist-info/METADATA
s1292013_learn-2024.7.29.1.dist-info/WHEEL
s1292013_learn-2024.7.29.1.dist-info/top_level.txt
s1292013_learn-2024.7.29.1.dist-info/RECORD
